MANIFEST.in
README.rst
setup.cfg
setup.py
scripts/ybot
scripts/ybot_setup
yahoo_fantasy_bot/__init__.py
yahoo_fantasy_bot/automation.py
yahoo_fantasy_bot/bot.py
yahoo_fantasy_bot/lineup_optimizer.py
yahoo_fantasy_bot/mlb.py
yahoo_fantasy_bot/nhl.py
yahoo_fantasy_bot/oauth2_logger.py
yahoo_fantasy_bot/roster.py
yahoo_fantasy_bot/scraper.py
yahoo_fantasy_bot/source.py
yahoo_fantasy_bot/utils.py
yahoo_fantasy_bot.egg-info/PKG-INFO
yahoo_fantasy_bot.egg-info/SOURCES.txt
yahoo_fantasy_bot.egg-info/dependency_links.txt
yahoo_fantasy_bot.egg-info/requires.txt
yahoo_fantasy_bot.egg-info/top_level.txt
yahoo_fantasy_bot.egg-info/zip-safe
yahoo_fantasy_bot/templates/sample_mlb_config.ini
yahoo_fantasy_bot/templates/sample_nhl_config.ini