Metadata-Version: 1.2
Name: yahoo-fantasy-bot
Version: 1.1.0
Summary: A bot that can act as a manager in a Yahoo! fantasy league
Home-page: http://github.com/spilchen/yahoo_fantasy_bot
Author: Matt Spilchen
Author-email: matt.spilchen@gmail.com
License: MIT
Platform: UNKNOWN
Classifier: Development Status :: 3 - Alpha
Classifier: Intended Audience :: Developers
Classifier: License :: OSI Approved :: MIT License
Classifier: Programming Language :: Python :: 3.5
Requires-Python: >=3
